{"id": 10150, "afinn": -33.0, "emotion": {"positive": 112, "trust": 88, "anger": 46, "disgust": 37, "negative": 76, "anticipation": 62, "joy": 53, "surprise": 39, "fear": 24, "sadness": 36}, "word_freq": {"husband": 23, "like": 21, "esh": 19, "sil": 17, "op": 12, "people": 12, "said": 12, "think": 11, "get": 11, "place": 11, "nta": 10, "really": 10, "home": 10, "could": 10, "also": 10, "everything": 10, "anything": 9, "comment": 8, "prenup": 8, "ah": 8, "went": 8, "even": 8, "r": 7, "amitheasshole": 7, "reddit": 7, "actually": 7, "made": 7, "family": 7, "marriage": 7, "look": 7}, "counts": {"nta_count": 10, "yta_count": 3, "esh_count": 19, "info_count": 1, "nah_count": 0}}