{"id": 10401, "afinn": 179.0, "emotion": {"positive": 488, "trust": 306, "anger": 167, "disgust": 140, "negative": 386, "anticipation": 285, "joy": 173, "sadness": 363, "fear": 236, "surprise": 71}, "word_freq": {"hospice": 88, "care": 87, "home": 65, "family": 61, "get": 61, "help": 59, "needs": 56, "time": 53, "dying": 51, "also": 42, "mom": 42, "going": 41, "fianc\u00e9": 40, "need": 39, "would": 38, "mother": 35, "make": 35, "want": 35, "take": 34, "fil": 33, "situation": 32, "child": 32, "mil": 32, "one": 31, "think": 29, "nah": 28, "husband": 27, "really": 26, "right": 26, "life": 25}, "counts": {"nta_count": 12, "yta_count": 10, "esh_count": 0, "info_count": 3, "nah_count": 28}}