{"id": 1045, "afinn": 213.0, "emotion": {"positive": 862, "trust": 258, "anger": 141, "disgust": 89, "negative": 358, "joy": 257, "anticipation": 152, "surprise": 83, "fear": 91, "sadness": 98}, "word_freq": {"jam": 189, "get": 185, "breakfast": 160, "bed": 142, "like": 100, "make": 76, "something": 69, "toast": 67, "would": 57, "made": 57, "could": 51, "nice": 51, "yta": 50, "eat": 46, "go": 42, "op": 40, "point": 40, "esh": 35, "nta": 33, "want": 32, "else": 32, "kitchen": 32, "bf": 31, "petty": 30, "asked": 30, "thing": 30, "kind": 30, "already": 30, "ask": 29, "one": 28}, "counts": {"nta_count": 33, "yta_count": 50, "esh_count": 35, "info_count": 7, "nah_count": 2}}