{"id": 10643, "afinn": -1154.0, "emotion": {"positive": 1507, "trust": 916, "anger": 772, "disgust": 385, "negative": 1418, "anticipation": 745, "joy": 621, "sadness": 734, "fear": 580, "surprise": 319}, "word_freq": {"son": 402, "wife": 398, "like": 219, "mother": 177, "mom": 134, "respect": 125, "alone": 114, "op": 108, "trying": 99, "get": 99, "would": 96, "way": 91, "leave": 91, "yta": 89, "parents": 88, "think": 81, "room": 81, "home": 79, "also": 78, "said": 75, "sounds": 73, "needs": 71, "know": 71, "going": 71, "something": 69, "space": 69, "people": 69, "kid": 66, "one": 65, "need": 65}, "counts": {"nta_count": 50, "yta_count": 89, "esh_count": 55, "info_count": 29, "nah_count": 1}}