{"id": 10821, "afinn": -352.0, "emotion": {"positive": 338, "trust": 198, "anger": 172, "disgust": 76, "negative": 356, "joy": 86, "anticipation": 190, "sadness": 139, "fear": 124, "surprise": 122}, "word_freq": {"like": 67, "people": 53, "interrupt": 52, "say": 51, "adhd": 46, "nta": 45, "rude": 43, "time": 41, "interrupting": 38, "would": 37, "get": 37, "talking": 34, "stop": 32, "saying": 31, "know": 31, "really": 29, "someone": 27, "joke": 27, "never": 26, "something": 26, "one": 24, "think": 24, "interrupted": 24, "finish": 23, "talk": 23, "tell": 21, "also": 21, "want": 21, "conversation": 20, "story": 20}, "counts": {"nta_count": 45, "yta_count": 3, "esh_count": 5, "info_count": 8, "nah_count": 2}}