{"id": 11456, "afinn": -17.0, "emotion": {"positive": 72, "trust": 60, "anger": 15, "disgust": 13, "negative": 62, "joy": 28, "anticipation": 37, "fear": 36, "surprise": 13, "sadness": 30}, "word_freq": {"tampons": 13, "use": 10, "period": 10, "mother": 10, "mom": 10, "nta": 9, "like": 9, "get": 8, "r": 7, "amitheasshole": 7, "https": 7, "www": 7, "com": 7, "wrong": 7, "reddit": 6, "keep": 6, "make": 6, "also": 6, "one": 5, "rules": 5, "swimming": 5, "school": 5, "way": 5, "issue": 5, "please": 4, "faq": 4, "allowed": 4, "well": 4, "try": 4, "swimwear": 4}, "counts": {"nta_count": 9, "yta_count": 0, "esh_count": 0, "info_count": 1, "nah_count": 0}}