{"id": 11482, "afinn": 86.0, "emotion": {"positive": 112, "trust": 62, "anger": 14, "disgust": 13, "negative": 52, "anticipation": 52, "joy": 40, "sadness": 18, "surprise": 20, "fear": 19}, "word_freq": {"nta": 23, "husband": 22, "parents": 18, "dishes": 15, "would": 15, "time": 15, "chores": 11, "could": 11, "like": 11, "house": 10, "work": 10, "done": 9, "still": 9, "cook": 9, "said": 9, "one": 8, "think": 8, "visit": 8, "laws": 8, "home": 8, "mil": 8, "table": 8, "r": 7, "amitheasshole": 7, "household": 7, "also": 7, "https": 6, "www": 6, "reddit": 6, "com": 6}, "counts": {"nta_count": 23, "yta_count": 0, "esh_count": 0, "info_count": 0, "nah_count": 0}}