{"id": 11619, "afinn": 76.0, "emotion": {"positive": 1169, "trust": 723, "anger": 324, "disgust": 164, "negative": 971, "joy": 366, "anticipation": 466, "fear": 419, "surprise": 172, "sadness": 461}, "word_freq": {"headphones": 366, "tv": 193, "noise": 183, "need": 167, "sound": 155, "volume": 151, "yta": 149, "people": 148, "loud": 146, "get": 141, "like": 133, "also": 126, "use": 114, "music": 111, "subtitles": 103, "wear": 102, "time": 94, "roommates": 93, "60": 91, "op": 90, "hear": 87, "autistic": 76, "needs": 75, "make": 73, "hearing": 73, "would": 73, "live": 71, "one": 69, "space": 64, "watch": 61}, "counts": {"nta_count": 8, "yta_count": 149, "esh_count": 2, "info_count": 4, "nah_count": 6}}