{"id": 11858, "afinn": 632.0, "emotion": {"positive": 949, "trust": 631, "anger": 264, "disgust": 209, "negative": 548, "joy": 402, "anticipation": 435, "fear": 284, "sadness": 281, "surprise": 212}, "word_freq": {"dad": 428, "like": 125, "yta": 118, "father": 118, "kid": 115, "7": 100, "talk": 93, "man": 89, "wife": 87, "things": 84, "know": 73, "stepson": 70, "son": 65, "different": 63, "make": 62, "way": 62, "time": 61, "good": 59, "need": 59, "old": 56, "going": 56, "get": 52, "step": 52, "kids": 50, "mom": 49, "talking": 48, "would": 48, "relationship": 46, "trying": 46, "something": 46}, "counts": {"nta_count": 7, "yta_count": 118, "esh_count": 7, "info_count": 1, "nah_count": 6}}