{"id": 11946, "afinn": 1648.0, "emotion": {"positive": 2775, "trust": 1698, "anger": 810, "disgust": 724, "negative": 1526, "sadness": 819, "joy": 1232, "anticipation": 1219, "surprise": 556, "fear": 632}, "word_freq": {"family": 701, "wife": 352, "wedding": 337, "culture": 312, "indian": 273, "lie": 271, "parents": 252, "would": 243, "married": 240, "want": 226, "think": 217, "like": 217, "know": 183, "op": 177, "relationship": 157, "one": 149, "get": 140, "people": 138, "even": 132, "go": 129, "way": 127, "marriage": 126, "lying": 116, "going": 115, "ceremony": 115, "understand": 112, "india": 111, "white": 102, "yta": 94, "make": 90}, "counts": {"nta_count": 47, "yta_count": 94, "esh_count": 18, "info_count": 10, "nah_count": 44}}