{"id": 12506, "afinn": -276.0, "emotion": {"positive": 696, "trust": 369, "anger": 173, "disgust": 162, "negative": 403, "anticipation": 386, "sadness": 260, "fear": 232, "surprise": 120, "joy": 413}, "word_freq": {"name": 526, "sister": 140, "family": 132, "child": 120, "nta": 118, "one": 95, "named": 89, "like": 81, "dylan": 81, "son": 80, "cousins": 79, "theodore": 75, "baby": 72, "use": 66, "first": 65, "would": 62, "died": 54, "names": 52, "op": 48, "kid": 48, "middle": 48, "wanted": 46, "grandfather": 44, "kids": 42, "people": 41, "think": 40, "going": 40, "get": 40, "even": 38, "cousin": 38}, "counts": {"nta_count": 118, "yta_count": 2, "esh_count": 8, "info_count": 4, "nah_count": 6}}