{"id": 12861, "afinn": 647.0, "emotion": {"positive": 3254, "trust": 1907, "anger": 382, "disgust": 378, "negative": 1423, "joy": 1288, "anticipation": 2127, "sadness": 760, "surprise": 569, "fear": 623}, "word_freq": {"time": 702, "daycare": 432, "op": 345, "clean": 340, "kids": 322, "day": 320, "child": 307, "kid": 267, "pick": 266, "like": 257, "would": 252, "teacher": 217, "sasha": 180, "get": 177, "parents": 176, "daughter": 172, "one": 169, "ready": 159, "know": 156, "late": 154, "nta": 152, "yta": 144, "rules": 143, "provider": 141, "parent": 138, "go": 137, "care": 136, "need": 134, "pickup": 134, "make": 133}, "counts": {"nta_count": 152, "yta_count": 144, "esh_count": 15, "info_count": 22, "nah_count": 17}}