{"id": 13807, "afinn": -76.0, "emotion": {"positive": 514, "trust": 313, "anger": 123, "disgust": 222, "negative": 383, "fear": 205, "sadness": 147, "joy": 288, "anticipation": 283, "surprise": 101}, "word_freq": {"sheets": 119, "husband": 80, "blood": 79, "nta": 64, "get": 64, "throw": 64, "baby": 62, "one": 59, "like": 48, "would": 44, "away": 42, "period": 42, "women": 41, "going": 41, "child": 41, "op": 40, "needs": 38, "periods": 37, "time": 32, "think": 28, "bleeding": 26, "gross": 26, "every": 26, "new": 24, "squeamish": 24, "years": 24, "even": 23, "normal": 22, "wash": 22, "help": 21}, "counts": {"nta_count": 64, "yta_count": 1, "esh_count": 0, "info_count": 3, "nah_count": 3}}