{"id": 14417, "afinn": -435.0, "emotion": {"positive": 886, "trust": 499, "anger": 516, "disgust": 430, "negative": 787, "joy": 349, "anticipation": 239, "fear": 277, "sadness": 376, "surprise": 135}, "word_freq": {"vegan": 219, "sheila": 147, "like": 130, "lying": 97, "people": 94, "nta": 86, "michaela": 79, "someone": 78, "lie": 76, "food": 73, "girlfriend": 71, "animal": 71, "gf": 69, "vegans": 69, "friend": 67, "would": 65, "op": 60, "vegetarian": 56, "also": 55, "think": 50, "one": 49, "esh": 44, "something": 43, "eat": 42, "make": 39, "lies": 39, "friends": 39, "get": 39, "even": 38, "really": 38}, "counts": {"nta_count": 86, "yta_count": 21, "esh_count": 44, "info_count": 0, "nah_count": 0}}