{"id": 14471, "afinn": 447.0, "emotion": {"positive": 1603, "trust": 1094, "anger": 370, "disgust": 415, "negative": 1147, "joy": 899, "anticipation": 869, "sadness": 583, "fear": 507, "surprise": 256}, "word_freq": {"mom": 393, "legs": 341, "shave": 321, "hair": 302, "shaving": 260, "like": 190, "nta": 176, "daughter": 141, "body": 131, "mother": 121, "would": 118, "12": 114, "think": 113, "dad": 113, "one": 107, "kid": 104, "allowed": 101, "let": 95, "even": 94, "age": 92, "time": 91, "make": 89, "child": 86, "want": 86, "also": 85, "back": 84, "old": 83, "leg": 80, "kids": 80, "get": 79}, "counts": {"nta_count": 176, "yta_count": 19, "esh_count": 7, "info_count": 4, "nah_count": 1}}