{"id": 14654, "afinn": -145.0, "emotion": {"positive": 114, "trust": 73, "anger": 28, "disgust": 20, "negative": 78, "joy": 32, "anticipation": 78, "sadness": 42, "fear": 33, "surprise": 32}, "word_freq": {"nta": 45, "car": 38, "garage": 23, "neighbor": 23, "towed": 21, "parked": 21, "park": 20, "get": 18, "work": 17, "parking": 15, "front": 12, "space": 12, "someone": 11, "one": 10, "move": 10, "40": 10, "even": 10, "time": 9, "would": 9, "know": 9, "r": 8, "amitheasshole": 8, "community": 8, "find": 8, "call": 8, "apartment": 8, "blocking": 8, "right": 8, "see": 8, "anyone": 8}, "counts": {"nta_count": 45, "yta_count": 1, "esh_count": 0, "info_count": 0, "nah_count": 0}}