{"id": 15113, "afinn": -567.0, "emotion": {"positive": 423, "trust": 250, "anger": 200, "disgust": 143, "negative": 364, "anticipation": 215, "joy": 202, "surprise": 73, "fear": 196, "sadness": 224}, "word_freq": {"son": 88, "nta": 74, "would": 67, "r": 62, "child": 53, "friend": 49, "sorry": 45, "like": 42, "loss": 42, "party": 38, "wife": 36, "tell": 34, "one": 31, "people": 30, "stranger": 28, "know": 28, "think": 27, "someone": 27, "parent": 27, "still": 26, "life": 26, "owe": 25, "op": 23, "even": 23, "something": 21, "apology": 20, "anything": 20, "comment": 19, "death": 19, "time": 19}, "counts": {"nta_count": 74, "yta_count": 0, "esh_count": 1, "info_count": 3, "nah_count": 0}}