{"id": 15321, "afinn": -586.0, "emotion": {"positive": 849, "trust": 614, "anger": 447, "disgust": 337, "negative": 1004, "fear": 433, "sadness": 425, "joy": 339, "anticipation": 412, "surprise": 216}, "word_freq": {"drink": 250, "friends": 247, "nta": 243, "would": 192, "waiter": 146, "like": 132, "one": 123, "soda": 114, "open": 111, "even": 99, "opened": 98, "something": 90, "could": 83, "get": 82, "also": 67, "made": 63, "new": 62, "unopened": 62, "people": 62, "right": 60, "know": 60, "someone": 60, "never": 58, "way": 58, "think": 55, "make": 55, "jokes": 54, "said": 52, "safety": 52, "drinks": 52}, "counts": {"nta_count": 243, "yta_count": 6, "esh_count": 3, "info_count": 2, "nah_count": 3}}