{"id": 15362, "afinn": 49.0, "emotion": {"positive": 289, "trust": 248, "anger": 50, "disgust": 40, "negative": 192, "joy": 127, "anticipation": 137, "fear": 69, "sadness": 72, "surprise": 40}, "word_freq": {"brother": 67, "room": 40, "cover": 37, "house": 34, "like": 32, "nta": 30, "breastfeeding": 24, "mom": 22, "uncomfortable": 22, "comfort": 22, "op": 21, "go": 21, "mother": 21, "mum": 20, "think": 19, "asked": 19, "leave": 19, "want": 17, "even": 16, "feed": 16, "people": 16, "feeding": 16, "else": 15, "breastfeed": 15, "one": 14, "time": 14, "blanket": 14, "baby": 14, "home": 14, "toddler": 14}, "counts": {"nta_count": 30, "yta_count": 12, "esh_count": 2, "info_count": 0, "nah_count": 1}}