{"id": 15508, "afinn": 179.0, "emotion": {"positive": 401, "trust": 302, "anger": 85, "disgust": 73, "negative": 196, "fear": 85, "sadness": 80, "joy": 285, "anticipation": 148, "surprise": 61}, "word_freq": {"ring": 126, "promise": 120, "get": 44, "nta": 43, "years": 39, "like": 37, "friend": 37, "rings": 34, "relationship": 32, "engagement": 32, "married": 24, "want": 22, "wants": 20, "would": 20, "5": 19, "one": 18, "think": 17, "got": 17, "laughed": 16, "30": 15, "laughing": 15, "marry": 14, "way": 14, "time": 14, "actually": 14, "even": 13, "together": 13, "going": 13, "thing": 12, "school": 12}, "counts": {"nta_count": 43, "yta_count": 4, "esh_count": 1, "info_count": 1, "nah_count": 1}}