{"id": 15668, "afinn": 949.0, "emotion": {"positive": 642, "trust": 475, "anger": 99, "disgust": 112, "negative": 266, "joy": 305, "anticipation": 174, "sadness": 121, "surprise": 87, "fear": 94}, "word_freq": {"best": 208, "nta": 160, "friend": 159, "brother": 155, "friends": 70, "close": 60, "girlfriend": 58, "gf": 50, "relationship": 48, "years": 47, "like": 43, "little": 36, "weird": 36, "call": 35, "one": 34, "sister": 34, "would": 33, "family": 33, "red": 31, "date": 31, "life": 31, "flag": 29, "think": 28, "siblings": 28, "younger": 27, "get": 27, "sounds": 26, "age": 25, "time": 24, "jealous": 23}, "counts": {"nta_count": 160, "yta_count": 0, "esh_count": 2, "info_count": 1, "nah_count": 1}}