{"id": 16322, "afinn": -37.0, "emotion": {"positive": 211, "trust": 118, "anger": 59, "disgust": 51, "negative": 163, "fear": 88, "joy": 105, "anticipation": 91, "sadness": 73, "surprise": 22}, "word_freq": {"nta": 73, "smoke": 49, "baby": 43, "smoking": 28, "clothes": 25, "mil": 21, "preemie": 19, "would": 19, "right": 18, "thank": 17, "child": 15, "health": 15, "smoker": 15, "welcome": 14, "hand": 14, "mom": 13, "like": 12, "time": 12, "really": 11, "parents": 11, "hold": 11, "around": 11, "still": 10, "let": 10, "see": 10, "kids": 10, "grandchildren": 10, "rules": 9, "important": 9, "get": 9}, "counts": {"nta_count": 73, "yta_count": 0, "esh_count": 0, "info_count": 2, "nah_count": 0}}