{"id": 16980, "afinn": 824.0, "emotion": {"positive": 1426, "trust": 795, "anger": 225, "disgust": 114, "negative": 339, "joy": 681, "anticipation": 545, "fear": 174, "sadness": 183, "surprise": 277}, "word_freq": {"restaurant": 148, "daughter": 143, "nta": 138, "would": 131, "go": 90, "like": 89, "dinner": 87, "one": 78, "budget": 75, "going": 73, "money": 73, "think": 72, "could": 68, "promise": 68, "make": 66, "take": 64, "family": 62, "year": 62, "sister": 60, "want": 60, "meal": 58, "expensive": 57, "get": 57, "maybe": 55, "also": 49, "things": 49, "time": 47, "something": 46, "might": 45, "good": 45}, "counts": {"nta_count": 138, "yta_count": 8, "esh_count": 1, "info_count": 2, "nah_count": 6}}