{"id": 17091, "afinn": -15.0, "emotion": {"positive": 240, "trust": 173, "anger": 61, "disgust": 55, "negative": 124, "anticipation": 107, "joy": 110, "fear": 70, "sadness": 70, "surprise": 39}, "word_freq": {"parents": 96, "kids": 66, "sex": 50, "siblings": 35, "nta": 34, "op": 32, "people": 30, "children": 26, "house": 25, "home": 24, "relationship": 24, "know": 23, "would": 22, "going": 22, "also": 21, "get": 20, "like": 20, "fetish": 19, "think": 18, "way": 17, "need": 17, "adults": 16, "one": 15, "anything": 14, "cps": 14, "sexual": 14, "something": 13, "parent": 13, "right": 13, "feel": 13}, "counts": {"nta_count": 34, "yta_count": 1, "esh_count": 1, "info_count": 0, "nah_count": 1}}