{"id": 17953, "afinn": 415.0, "emotion": {"positive": 1052, "trust": 561, "anger": 285, "disgust": 187, "negative": 668, "sadness": 288, "anticipation": 631, "joy": 529, "surprise": 269, "fear": 253}, "word_freq": {"room": 230, "bunk": 213, "bed": 188, "go": 186, "mil": 170, "kids": 154, "would": 141, "nta": 138, "queen": 130, "like": 127, "one": 121, "beds": 118, "get": 111, "husband": 106, "family": 105, "make": 92, "op": 87, "going": 77, "want": 71, "rooms": 70, "trip": 69, "time": 66, "vacation": 65, "kid": 65, "foster": 62, "way": 60, "child": 56, "could": 55, "people": 55, "even": 55}, "counts": {"nta_count": 138, "yta_count": 2, "esh_count": 2, "info_count": 13, "nah_count": 1}}