{"id": 18035, "afinn": 347.0, "emotion": {"positive": 1551, "trust": 1000, "anger": 555, "disgust": 306, "negative": 1073, "fear": 369, "sadness": 523, "joy": 738, "anticipation": 944, "surprise": 488}, "word_freq": {"hair": 452, "like": 177, "nta": 163, "would": 154, "get": 140, "black": 120, "respect": 112, "think": 110, "money": 108, "boundaries": 108, "people": 98, "time": 95, "something": 89, "know": 87, "water": 87, "even": 86, "white": 79, "really": 73, "someone": 71, "important": 67, "make": 65, "understand": 64, "done": 62, "care": 62, "way": 60, "big": 60, "told": 58, "want": 57, "relationship": 56, "needs": 55}, "counts": {"nta_count": 163, "yta_count": 2, "esh_count": 5, "info_count": 6, "nah_count": 8}}