{"id": 18905, "afinn": 39.0, "emotion": {"positive": 153, "trust": 103, "anger": 43, "disgust": 34, "negative": 90, "anticipation": 73, "joy": 80, "surprise": 32, "fear": 40, "sadness": 39}, "word_freq": {"would": 25, "get": 23, "food": 22, "rm": 21, "nta": 20, "gf": 17, "room": 16, "like": 16, "one": 15, "roommate": 15, "know": 15, "lease": 15, "make": 14, "post": 14, "friends": 13, "days": 13, "cook": 12, "lock": 12, "even": 11, "guest": 10, "want": 10, "said": 10, "r": 9, "ss": 9, "never": 9, "amitheasshole": 8, "reddit": 8, "door": 8, "money": 8, "time": 8}, "counts": {"nta_count": 20, "yta_count": 0, "esh_count": 2, "info_count": 1, "nah_count": 0}}