{"id": 19029, "afinn": -165.0, "emotion": {"positive": 759, "trust": 522, "anger": 211, "disgust": 133, "negative": 504, "anticipation": 336, "joy": 309, "sadness": 361, "fear": 240, "surprise": 111}, "word_freq": {"nta": 322, "brother": 136, "mother": 107, "mom": 96, "siblings": 86, "take": 82, "let": 78, "back": 69, "care": 65, "family": 62, "children": 54, "life": 51, "nothing": 49, "home": 47, "owe": 47, "live": 46, "abandoned": 45, "would": 44, "like": 42, "even": 42, "time": 41, "get": 40, "problem": 36, "years": 36, "one": 33, "younger": 32, "woman": 32, "anything": 30, "go": 29, "made": 28}, "counts": {"nta_count": 322, "yta_count": 2, "esh_count": 0, "info_count": 0, "nah_count": 0}}