{"id": 19050, "afinn": -323.0, "emotion": {"positive": 362, "trust": 261, "anger": 178, "disgust": 147, "negative": 354, "joy": 153, "anticipation": 184, "sadness": 190, "fear": 162, "surprise": 83}, "word_freq": {"wife": 137, "family": 125, "kids": 59, "want": 55, "like": 47, "wedding": 46, "yta": 40, "go": 38, "invited": 36, "get": 36, "going": 32, "children": 32, "cheated": 32, "chronic": 30, "op": 26, "would": 26, "infidelity": 25, "also": 25, "years": 25, "sister": 23, "know": 23, "around": 22, "need": 21, "still": 21, "take": 21, "without": 20, "one": 19, "even": 19, "think": 18, "consequences": 18}, "counts": {"nta_count": 4, "yta_count": 40, "esh_count": 0, "info_count": 9, "nah_count": 0}}