{"id": 1954, "afinn": -118.0, "emotion": {"positive": 976, "trust": 463, "anger": 388, "disgust": 163, "negative": 805, "anticipation": 696, "joy": 261, "surprise": 199, "fear": 299, "sadness": 289}, "word_freq": {"yta": 192, "board": 190, "boarding": 186, "plane": 181, "get": 153, "group": 136, "like": 132, "would": 123, "minutes": 114, "first": 101, "people": 100, "op": 97, "together": 94, "time": 93, "5": 80, "think": 77, "argument": 73, "one": 71, "even": 71, "travel": 71, "wait": 71, "seat": 70, "groups": 68, "boarded": 67, "big": 65, "seasoned": 62, "priority": 60, "going": 60, "really": 58, "always": 58}, "counts": {"nta_count": 22, "yta_count": 192, "esh_count": 8, "info_count": 4, "nah_count": 11}}