{"id": 1965, "afinn": -251.0, "emotion": {"positive": 845, "trust": 624, "anger": 385, "disgust": 331, "negative": 832, "joy": 313, "anticipation": 348, "fear": 316, "sadness": 391, "surprise": 170}, "word_freq": {"dog": 575, "wife": 412, "get": 188, "yta": 184, "therapy": 154, "issues": 131, "like": 129, "house": 124, "help": 100, "needs": 97, "clothes": 97, "sensory": 93, "training": 91, "train": 90, "even": 87, "want": 77, "dogs": 67, "also": 67, "would": 66, "getting": 64, "need": 59, "health": 52, "trained": 51, "wants": 49, "mental": 49, "one": 48, "let": 48, "make": 47, "sounds": 46, "care": 43}, "counts": {"nta_count": 8, "yta_count": 184, "esh_count": 7, "info_count": 5, "nah_count": 0}}