{"id": 19741, "afinn": 253.0, "emotion": {"positive": 2006, "trust": 933, "anger": 460, "disgust": 394, "negative": 944, "joy": 1096, "anticipation": 621, "sadness": 538, "fear": 540, "surprise": 275}, "word_freq": {"baby": 517, "son": 484, "wife": 342, "hold": 311, "sister": 228, "holding": 156, "like": 155, "old": 148, "nta": 134, "would": 127, "op": 116, "family": 116, "step": 113, "brother": 112, "one": 111, "half": 110, "14": 108, "let": 107, "sibling": 105, "get": 102, "make": 98, "year": 98, "even": 97, "mom": 93, "siblings": 91, "new": 89, "think": 85, "child": 83, "kids": 82, "first": 81}, "counts": {"nta_count": 134, "yta_count": 15, "esh_count": 18, "info_count": 18, "nah_count": 3}}