{"id": 20091, "afinn": -100.0, "emotion": {"positive": 211, "trust": 149, "anger": 102, "disgust": 102, "negative": 192, "fear": 107, "sadness": 118, "anticipation": 107, "joy": 86, "surprise": 58}, "word_freq": {"nta": 50, "like": 29, "stop": 28, "time": 24, "father": 23, "dad": 23, "make": 19, "comment": 17, "op": 16, "r": 15, "amitheasshole": 15, "weight": 15, "https": 14, "www": 14, "reddit": 14, "com": 14, "one": 14, "go": 14, "would": 14, "years": 14, "asshole": 13, "apology": 12, "going": 11, "motivation": 11, "lunch": 11, "mean": 11, "told": 11, "get": 11, "comments": 10, "cruel": 10}, "counts": {"nta_count": 50, "yta_count": 0, "esh_count": 0, "info_count": 1, "nah_count": 0}}