{"id": 20712, "afinn": -258.0, "emotion": {"positive": 840, "trust": 511, "anger": 279, "disgust": 215, "negative": 790, "fear": 444, "sadness": 599, "joy": 367, "anticipation": 413, "surprise": 177}, "word_freq": {"katie": 241, "parents": 164, "family": 125, "buried": 113, "dad": 101, "like": 89, "siblings": 77, "wishes": 74, "one": 68, "would": 65, "half": 63, "brother": 62, "nta": 61, "even": 60, "kids": 59, "really": 56, "mother": 49, "mom": 48, "op": 46, "get": 46, "want": 44, "sister": 43, "parent": 43, "19": 41, "alone": 40, "child": 40, "life": 40, "never": 40, "could": 38, "going": 38}, "counts": {"nta_count": 61, "yta_count": 4, "esh_count": 8, "info_count": 5, "nah_count": 33}}