{"id": 21204, "afinn": -932.0, "emotion": {"positive": 751, "trust": 614, "anger": 440, "disgust": 208, "negative": 805, "fear": 463, "sadness": 380, "anticipation": 410, "joy": 276, "surprise": 189}, "word_freq": {"car": 501, "sister": 202, "report": 194, "stolen": 159, "nta": 145, "mom": 137, "get": 110, "would": 95, "insurance": 94, "back": 85, "police": 82, "call": 76, "kids": 63, "could": 60, "also": 60, "mother": 59, "take": 59, "give": 56, "one": 51, "op": 49, "time": 48, "need": 45, "vehicle": 45, "go": 43, "going": 42, "like": 42, "use": 41, "accident": 40, "tell": 40, "driver": 40}, "counts": {"nta_count": 145, "yta_count": 2, "esh_count": 0, "info_count": 2, "nah_count": 0}}