{"id": 22786, "afinn": -229.0, "emotion": {"positive": 401, "trust": 281, "anger": 226, "disgust": 154, "negative": 372, "joy": 152, "anticipation": 191, "sadness": 217, "fear": 153, "surprise": 70}, "word_freq": {"wife": 119, "parents": 97, "like": 64, "mom": 50, "kids": 43, "mil": 43, "op": 41, "people": 39, "family": 37, "way": 36, "nta": 36, "get": 32, "rude": 31, "mother": 31, "say": 29, "things": 28, "speak": 26, "would": 25, "think": 24, "know": 24, "esh": 24, "bad": 23, "post": 22, "someone": 22, "tell": 22, "feel": 22, "censoring": 20, "want": 20, "talk": 20, "divorce": 20}, "counts": {"nta_count": 36, "yta_count": 8, "esh_count": 24, "info_count": 4, "nah_count": 0}}