{"id": 22818, "afinn": 16.0, "emotion": {"positive": 114, "trust": 93, "anger": 35, "disgust": 23, "negative": 67, "joy": 47, "anticipation": 54, "fear": 34, "sadness": 31, "surprise": 35}, "word_freq": {"nta": 26, "father": 24, "relationship": 14, "would": 12, "dad": 12, "like": 11, "uncle": 11, "want": 10, "time": 10, "go": 10, "know": 9, "tell": 9, "thanksgiving": 9, "sibling": 9, "talk": 9, "life": 9, "r": 8, "amitheasshole": 8, "please": 8, "feel": 8, "wants": 8, "get": 8, "said": 8, "good": 8, "https": 7, "www": 7, "reddit": 7, "com": 7, "going": 7, "cut": 7}, "counts": {"nta_count": 26, "yta_count": 1, "esh_count": 0, "info_count": 0, "nah_count": 1}}