{"id": 23740, "afinn": -170.0, "emotion": {"positive": 398, "trust": 242, "anger": 196, "disgust": 151, "negative": 498, "sadness": 348, "anticipation": 237, "fear": 344, "joy": 157, "surprise": 104}, "word_freq": {"dog": 244, "james": 99, "nta": 89, "left": 72, "ex": 68, "would": 66, "know": 50, "could": 47, "right": 42, "sorry": 41, "surgery": 41, "even": 41, "op": 40, "best": 40, "thing": 39, "made": 37, "let": 37, "decision": 35, "like": 33, "life": 32, "care": 31, "loss": 31, "make": 31, "time": 31, "one": 30, "vet": 29, "loved": 28, "think": 27, "pet": 27, "call": 27}, "counts": {"nta_count": 89, "yta_count": 14, "esh_count": 8, "info_count": 7, "nah_count": 1}}