{"id": 23804, "afinn": -616.0, "emotion": {"positive": 797, "trust": 715, "anger": 273, "disgust": 236, "negative": 770, "anticipation": 565, "joy": 501, "fear": 422, "surprise": 268, "sadness": 425}, "word_freq": {"dress": 282, "nta": 224, "wedding": 150, "mother": 148, "mom": 126, "marry": 117, "want": 100, "try": 99, "would": 98, "fianc\u00e9": 97, "get": 94, "fiance": 82, "back": 72, "like": 70, "let": 62, "boundaries": 58, "fmil": 57, "future": 54, "think": 52, "man": 52, "going": 52, "really": 50, "problem": 46, "tried": 46, "go": 46, "mommy": 45, "run": 44, "see": 44, "mil": 43, "knew": 43}, "counts": {"nta_count": 224, "yta_count": 0, "esh_count": 16, "info_count": 4, "nah_count": 0}}