{"id": 24269, "afinn": 322.0, "emotion": {"positive": 521, "trust": 349, "anger": 209, "disgust": 131, "negative": 418, "surprise": 174, "anticipation": 407, "joy": 214, "fear": 211, "sadness": 211}, "word_freq": {"son": 140, "time": 116, "kids": 90, "yta": 86, "weekend": 83, "trip": 75, "see": 69, "like": 66, "ex": 57, "go": 56, "get": 55, "would": 51, "want": 48, "kid": 47, "one": 46, "boyfriend": 46, "things": 45, "make": 44, "child": 42, "know": 42, "mom": 41, "let": 41, "think": 40, "weekends": 40, "say": 40, "going": 37, "could": 34, "something": 33, "custody": 30, "jealous": 30}, "counts": {"nta_count": 10, "yta_count": 86, "esh_count": 0, "info_count": 7, "nah_count": 4}}