{"id": 26022, "afinn": -50.0, "emotion": {"positive": 2448, "trust": 1600, "anger": 609, "disgust": 485, "negative": 1418, "fear": 745, "anticipation": 1200, "joy": 1064, "surprise": 296, "sadness": 754}, "word_freq": {"kids": 603, "wife": 318, "get": 313, "children": 272, "want": 249, "sex": 236, "yta": 220, "control": 207, "vasectomy": 205, "two": 194, "birth": 187, "pregnant": 182, "like": 163, "help": 156, "twins": 155, "one": 153, "take": 151, "pill": 146, "need": 144, "wanted": 140, "could": 135, "care": 133, "even": 128, "time": 121, "would": 118, "responsibility": 117, "op": 116, "condoms": 116, "got": 110, "also": 110}, "counts": {"nta_count": 25, "yta_count": 220, "esh_count": 81, "info_count": 4, "nah_count": 3}}