{"id": 26472, "afinn": 28.0, "emotion": {"positive": 105, "trust": 86, "anger": 19, "disgust": 7, "negative": 51, "anticipation": 63, "joy": 54, "surprise": 18, "sadness": 29, "fear": 13}, "word_freq": {"car": 36, "use": 26, "gas": 26, "mother": 19, "nta": 17, "money": 11, "pay": 11, "much": 11, "brother": 11, "r": 10, "amitheasshole": 10, "think": 10, "https": 9, "reddit": 9, "com": 9, "family": 9, "time": 9, "move": 9, "www": 8, "put": 8, "need": 8, "would": 8, "op": 7, "want": 7, "also": 7, "like": 7, "rent": 7, "fill": 7, "one": 6, "using": 6}, "counts": {"nta_count": 17, "yta_count": 0, "esh_count": 0, "info_count": 2, "nah_count": 0}}