{"id": 26499, "afinn": -3.0, "emotion": {"positive": 123, "trust": 63, "anger": 36, "disgust": 22, "negative": 62, "sadness": 35, "anticipation": 74, "joy": 44, "fear": 22, "surprise": 23}, "word_freq": {"x200b": 73, "cousin": 31, "nta": 24, "pick": 21, "mom": 17, "rent": 14, "tell": 14, "years": 13, "get": 12, "5": 11, "free": 11, "r": 10, "amitheasshole": 10, "airport": 10, "time": 10, "let": 10, "living": 10, "https": 9, "reddit": 9, "com": 9, "live": 9, "www": 8, "like": 8, "mother": 8, "move": 8, "go": 7, "needs": 7, "place": 7, "think": 6, "plans": 6}, "counts": {"nta_count": 24, "yta_count": 1, "esh_count": 0, "info_count": 0, "nah_count": 0}}