{"id": 26700, "afinn": -64.0, "emotion": {"positive": 221, "trust": 128, "anger": 60, "disgust": 32, "negative": 182, "sadness": 94, "anticipation": 229, "joy": 56, "surprise": 48, "fear": 62}, "word_freq": {"time": 73, "appointment": 54, "nta": 40, "minutes": 38, "wait": 35, "dentist": 30, "get": 28, "late": 28, "would": 26, "patients": 25, "waiting": 23, "one": 21, "doctor": 19, "doctors": 18, "hour": 17, "long": 16, "people": 16, "see": 15, "fee": 14, "make": 14, "longer": 14, "30": 14, "pay": 13, "could": 13, "patient": 13, "room": 13, "day": 13, "new": 12, "need": 12, "still": 12}, "counts": {"nta_count": 40, "yta_count": 0, "esh_count": 0, "info_count": 0, "nah_count": 2}}