{"id": 26859, "afinn": 92.0, "emotion": {"positive": 80, "trust": 35, "anger": 21, "disgust": 24, "negative": 56, "joy": 36, "anticipation": 31, "sadness": 17, "surprise": 12, "fear": 13}, "word_freq": {"pregnancy": 15, "time": 14, "nta": 13, "husband": 11, "r": 10, "amitheasshole": 10, "help": 10, "friends": 10, "text": 10, "back": 10, "https": 9, "reddit": 9, "com": 9, "friendship": 9, "take": 9, "need": 9, "www": 8, "one": 8, "post": 8, "want": 8, "crib": 7, "still": 7, "support": 7, "everyone": 7, "thank": 7, "think": 6, "get": 6, "go": 6, "make": 6, "way": 6}, "counts": {"nta_count": 13, "yta_count": 0, "esh_count": 2, "info_count": 0, "nah_count": 4}}