{"id": 27121, "afinn": 2.0, "emotion": {"positive": 31, "trust": 18, "anger": 8, "disgust": 3, "negative": 17, "joy": 9, "anticipation": 19, "sadness": 6, "surprise": 6, "fear": 16}, "word_freq": {"line": 14, "r": 10, "amitheasshole": 10, "https": 9, "reddit": 9, "com": 9, "www": 8, "said": 8, "nta": 8, "people": 6, "boarding": 6, "cut": 6, "get": 5, "large": 5, "group": 5, "back": 5, "board": 5, "front": 5, "please": 4, "faq": 4, "one": 4, "subreddit": 4, "queuing": 4, "everyone": 4, "man": 4, "tried": 4, "wiki": 3, "comment": 3, "else": 3, "comments": 3}, "counts": {"nta_count": 8, "yta_count": 0, "esh_count": 0, "info_count": 1, "nah_count": 0}}