{"id": 28035, "afinn": 644.0, "emotion": {"positive": 2260, "trust": 1499, "anger": 489, "disgust": 376, "negative": 1105, "joy": 1075, "anticipation": 1305, "surprise": 429, "fear": 645, "sadness": 542}, "word_freq": {"wife": 414, "emily": 287, "like": 275, "step": 233, "dad": 223, "time": 223, "would": 212, "child": 210, "op": 209, "kids": 209, "kid": 200, "nta": 190, "get": 185, "family": 178, "daughter": 174, "parent": 173, "golf": 163, "father": 161, "figure": 157, "need": 143, "even": 136, "also": 132, "siblings": 128, "without": 120, "one": 119, "babysitter": 118, "want": 115, "life": 113, "needs": 111, "saturday": 111}, "counts": {"nta_count": 190, "yta_count": 33, "esh_count": 40, "info_count": 9, "nah_count": 2}}