{"id": 28275, "afinn": 1106.0, "emotion": {"positive": 1311, "trust": 763, "anger": 495, "disgust": 225, "negative": 703, "joy": 760, "surprise": 420, "anticipation": 766, "fear": 203, "sadness": 252}, "word_freq": {"blender": 224, "money": 197, "like": 166, "one": 123, "husband": 114, "fun": 100, "get": 96, "nta": 95, "would": 84, "something": 75, "make": 74, "time": 73, "got": 73, "petty": 70, "good": 68, "bought": 62, "use": 58, "much": 55, "want": 55, "even": 54, "made": 53, "really": 51, "things": 51, "125": 50, "kitchen": 49, "every": 48, "also": 46, "think": 45, "way": 45, "op": 43}, "counts": {"nta_count": 95, "yta_count": 9, "esh_count": 25, "info_count": 9, "nah_count": 2}}