{"id": 30368, "afinn": -74.0, "emotion": {"positive": 1762, "trust": 960, "anger": 479, "disgust": 362, "negative": 1249, "joy": 755, "anticipation": 607, "fear": 586, "sadness": 504, "surprise": 342}, "word_freq": {"alcohol": 484, "husband": 268, "drink": 254, "wine": 248, "drinking": 195, "glass": 169, "daughter": 163, "like": 152, "parents": 150, "would": 146, "first": 141, "think": 137, "16": 132, "nta": 127, "kids": 114, "home": 110, "one": 108, "way": 107, "also": 105, "family": 102, "age": 98, "op": 95, "yta": 93, "decision": 91, "never": 84, "get": 82, "try": 82, "let": 80, "even": 80, "make": 80}, "counts": {"nta_count": 127, "yta_count": 93, "esh_count": 15, "info_count": 6, "nah_count": 18}}