{"id": 30948, "afinn": 138.0, "emotion": {"positive": 190, "trust": 122, "anger": 37, "disgust": 18, "negative": 71, "anticipation": 98, "fear": 60, "joy": 93, "sadness": 48, "surprise": 28}, "word_freq": {"wife": 52, "parents": 24, "birth": 22, "want": 18, "tell": 17, "baby": 14, "people": 13, "nta": 12, "r": 11, "like": 11, "wants": 11, "fair": 10, "hospital": 10, "get": 9, "amitheasshole": 8, "https": 8, "reddit": 8, "com": 8, "anyone": 8, "know": 8, "boundaries": 8, "room": 8, "mom": 8, "mother": 8, "www": 7, "one": 7, "would": 7, "much": 7, "delivery": 7, "visit": 7}, "counts": {"nta_count": 12, "yta_count": 0, "esh_count": 0, "info_count": 1, "nah_count": 0}}