{"id": 31114, "afinn": -87.0, "emotion": {"positive": 109, "trust": 86, "anger": 52, "disgust": 36, "negative": 99, "joy": 48, "anticipation": 47, "sadness": 48, "fear": 40, "surprise": 10}, "word_freq": {"use": 35, "nta": 34, "utensils": 30, "lea": 28, "roommates": 25, "get": 18, "kitchen": 15, "buy": 15, "rules": 14, "kosher": 14, "people": 13, "rent": 12, "things": 12, "pans": 12, "meat": 12, "right": 11, "like": 11, "dairy": 11, "respect": 10, "r": 9, "https": 9, "com": 9, "entitled": 9, "religious": 9, "move": 9, "stuff": 9, "amitheasshole": 8, "www": 8, "reddit": 8, "paying": 8}, "counts": {"nta_count": 34, "yta_count": 0, "esh_count": 0, "info_count": 0, "nah_count": 0}}