{"id": 3133, "afinn": 65.0, "emotion": {"positive": 215, "trust": 133, "anger": 41, "disgust": 32, "negative": 89, "surprise": 30, "joy": 106, "anticipation": 105, "fear": 61, "sadness": 60}, "word_freq": {"child": 34, "would": 32, "bil": 32, "sil": 26, "family": 25, "husband": 25, "godparents": 24, "nta": 17, "godmother": 16, "pick": 16, "one": 15, "choose": 15, "want": 14, "kids": 14, "godfather": 14, "brother": 14, "god": 14, "married": 14, "like": 14, "someone": 13, "might": 11, "laws": 11, "godparent": 11, "parents": 11, "people": 11, "children": 10, "treat": 10, "make": 9, "also": 9, "get": 9}, "counts": {"nta_count": 17, "yta_count": 2, "esh_count": 0, "info_count": 1, "nah_count": 0}}