{"id": 3217, "afinn": -520.0, "emotion": {"positive": 2095, "trust": 979, "anger": 525, "disgust": 409, "negative": 1086, "joy": 1168, "fear": 600, "anticipation": 1006, "surprise": 485, "sadness": 682}, "word_freq": {"aunt": 357, "nta": 265, "birthday": 212, "child": 202, "old": 189, "like": 181, "kid": 181, "cousin": 153, "8": 149, "op": 144, "baby": 126, "year": 123, "family": 123, "get": 122, "rainbow": 121, "would": 119, "miscarriages": 116, "behavior": 113, "brat": 112, "know": 108, "said": 107, "way": 99, "one": 98, "daughter": 92, "better": 85, "little": 83, "ruined": 78, "someone": 76, "think": 74, "people": 74}, "counts": {"nta_count": 265, "yta_count": 19, "esh_count": 20, "info_count": 2, "nah_count": 0}}