{"id": 32320, "afinn": -23.0, "emotion": {"positive": 51, "trust": 43, "anger": 15, "disgust": 6, "negative": 39, "anticipation": 24, "fear": 20, "surprise": 11, "sadness": 15, "joy": 24}, "word_freq": {"nta": 12, "car": 9, "r": 8, "amitheasshole": 8, "work": 8, "https": 7, "reddit": 7, "com": 7, "risk": 7, "still": 7, "www": 6, "would": 6, "friend": 6, "rental": 6, "trust": 6, "even": 5, "help": 5, "pay": 5, "past": 5, "way": 5, "told": 5, "like": 5, "someone": 5, "faq": 4, "use": 4, "one": 4, "repeat": 4, "incident": 4, "action": 4, "post": 4}, "counts": {"nta_count": 12, "yta_count": 1, "esh_count": 0, "info_count": 0, "nah_count": 0}}