{"id": 3996, "afinn": -11.0, "emotion": {"positive": 130, "trust": 81, "anger": 56, "disgust": 17, "negative": 95, "fear": 43, "anticipation": 74, "joy": 57, "surprise": 35, "sadness": 47}, "word_freq": {"parents": 25, "apology": 19, "like": 15, "money": 15, "gf": 13, "girlfriend": 12, "nta": 12, "sum": 12, "want": 11, "see": 10, "would": 10, "lump": 10, "people": 8, "say": 8, "make": 8, "r": 7, "amitheasshole": 7, "one": 7, "time": 7, "going": 7, "get": 7, "said": 7, "predatory": 7, "anything": 7, "https": 6, "www": 6, "reddit": 6, "com": 6, "know": 6, "take": 6}, "counts": {"nta_count": 12, "yta_count": 2, "esh_count": 0, "info_count": 2, "nah_count": 0}}