{"id": 4383, "afinn": -322.0, "emotion": {"positive": 819, "trust": 740, "anger": 225, "disgust": 154, "negative": 547, "joy": 189, "anticipation": 340, "fear": 419, "sadness": 280, "surprise": 126}, "word_freq": {"dad": 207, "nta": 120, "tell": 92, "doctor": 90, "father": 84, "need": 77, "advice": 75, "get": 73, "like": 72, "medical": 72, "please": 64, "sugar": 60, "know": 58, "life": 57, "mom": 51, "op": 50, "health": 49, "milk": 48, "go": 43, "going": 40, "step": 40, "could": 39, "right": 39, "also": 38, "needs": 37, "doctors": 37, "trying": 36, "listen": 36, "would": 36, "time": 36}, "counts": {"nta_count": 120, "yta_count": 0, "esh_count": 0, "info_count": 3, "nah_count": 0}}