{"id": 5199, "afinn": 2024.0, "emotion": {"positive": 1628, "trust": 961, "anger": 395, "disgust": 245, "negative": 787, "fear": 382, "sadness": 561, "anticipation": 724, "joy": 1030, "surprise": 283}, "word_freq": {"mom": 366, "love": 239, "dad": 194, "like": 193, "feel": 172, "mother": 142, "step": 133, "think": 127, "feelings": 125, "would": 109, "never": 107, "first": 106, "way": 102, "family": 100, "christmas": 97, "op": 93, "stepmom": 93, "parent": 91, "see": 89, "nta": 82, "one": 77, "relationship": 76, "child": 75, "said": 73, "even": 70, "baby": 69, "know": 66, "want": 65, "make": 64, "say": 64}, "counts": {"nta_count": 82, "yta_count": 16, "esh_count": 6, "info_count": 4, "nah_count": 38}}