{"id": 5591, "afinn": -378.0, "emotion": {"positive": 101, "trust": 63, "anger": 117, "disgust": 73, "negative": 176, "fear": 82, "sadness": 88, "anticipation": 45, "joy": 32, "surprise": 24}, "word_freq": {"nta": 45, "people": 25, "property": 20, "would": 19, "even": 18, "someone": 18, "one": 13, "earphones": 13, "think": 12, "airpods": 12, "right": 12, "asshole": 11, "wired": 11, "tiktok": 11, "like": 11, "things": 11, "headphones": 10, "still": 9, "damage": 9, "friends": 9, "video": 9, "stranger": 9, "sentimental": 8, "stupid": 8, "trend": 8, "get": 8, "something": 8, "really": 8, "r": 7, "amitheasshole": 7}, "counts": {"nta_count": 45, "yta_count": 0, "esh_count": 0, "info_count": 0, "nah_count": 0}}