{"id": 5743, "afinn": -23.0, "emotion": {"positive": 499, "trust": 305, "anger": 89, "disgust": 106, "negative": 211, "joy": 304, "fear": 82, "sadness": 77, "anticipation": 149, "surprise": 57}, "word_freq": {"daughter": 115, "friend": 56, "brother": 54, "sex": 50, "would": 37, "know": 32, "yta": 31, "nta": 29, "tell": 29, "prostitute": 27, "think": 25, "like": 25, "one": 24, "people": 23, "op": 21, "telling": 21, "want": 21, "even": 21, "someone": 21, "also": 20, "good": 18, "told": 18, "need": 17, "worker": 16, "could": 16, "still": 14, "work": 14, "age": 14, "said": 14, "way": 13}, "counts": {"nta_count": 29, "yta_count": 31, "esh_count": 3, "info_count": 3, "nah_count": 0}}