{"id": 6549, "afinn": -96.0, "emotion": {"positive": 155, "trust": 102, "anger": 69, "disgust": 84, "negative": 143, "sadness": 53, "joy": 61, "anticipation": 94, "surprise": 23, "fear": 68}, "word_freq": {"outside": 46, "pee": 44, "nta": 29, "see": 24, "like": 24, "yard": 21, "get": 17, "one": 16, "peeing": 16, "think": 15, "toilet": 15, "registry": 15, "neighbors": 15, "even": 13, "house": 13, "public": 12, "people": 11, "would": 11, "go": 11, "bathroom": 10, "back": 10, "far": 10, "urination": 10, "want": 9, "child": 9, "us": 9, "pretty": 9, "going": 9, "really": 9, "live": 9}, "counts": {"nta_count": 29, "yta_count": 8, "esh_count": 0, "info_count": 4, "nah_count": 1}}