{"id": 6820, "afinn": 150.0, "emotion": {"positive": 1176, "trust": 648, "anger": 338, "disgust": 290, "negative": 667, "fear": 320, "joy": 747, "anticipation": 752, "sadness": 396, "surprise": 200}, "word_freq": {"child": 317, "nta": 167, "parents": 157, "take": 157, "sister": 143, "would": 138, "family": 131, "life": 111, "kid": 106, "want": 102, "care": 80, "get": 78, "responsibility": 76, "nephew": 75, "one": 69, "mother": 68, "op": 60, "foster": 58, "kids": 58, "adopt": 57, "like": 56, "could": 56, "state": 54, "situation": 51, "baby": 50, "mom": 49, "going": 47, "even": 44, "another": 41, "may": 41}, "counts": {"nta_count": 167, "yta_count": 13, "esh_count": 8, "info_count": 3, "nah_count": 7}}