{"id": 7157, "afinn": -115.0, "emotion": {"positive": 247, "trust": 165, "anger": 106, "disgust": 75, "negative": 246, "fear": 137, "sadness": 143, "surprise": 99, "joy": 107, "anticipation": 167}, "word_freq": {"chair": 58, "husband": 50, "mil": 42, "like": 36, "go": 28, "op": 25, "nta": 25, "would": 23, "said": 20, "one": 19, "something": 19, "broke": 19, "replace": 19, "think": 17, "say": 17, "time": 17, "break": 16, "going": 15, "get": 14, "pay": 13, "house": 12, "feel": 12, "someone": 12, "way": 12, "told": 12, "200": 12, "right": 11, "even": 11, "make": 11, "people": 11}, "counts": {"nta_count": 25, "yta_count": 0, "esh_count": 4, "info_count": 2, "nah_count": 1}}