{"id": 7651, "afinn": -19.0, "emotion": {"positive": 78, "trust": 28, "anger": 16, "disgust": 8, "negative": 36, "anticipation": 57, "fear": 13, "joy": 13, "sadness": 11, "surprise": 9}, "word_freq": {"delivery": 23, "neighbor": 19, "package": 12, "packages": 11, "nta": 11, "door": 10, "guy": 8, "get": 8, "deliver": 8, "r": 7, "amitheasshole": 7, "https": 7, "reddit": 7, "anything": 7, "www": 6, "com": 6, "service": 6, "stop": 5, "even": 5, "back": 5, "asked": 5, "never": 5, "per": 5, "us": 5, "mom": 5, "faq": 4, "getting": 4, "neighbors": 4, "5": 4, "post": 4}, "counts": {"nta_count": 11, "yta_count": 0, "esh_count": 0, "info_count": 0, "nah_count": 0}}