{"id": 7744, "afinn": 63.0, "emotion": {"positive": 338, "trust": 216, "anger": 79, "disgust": 89, "negative": 240, "joy": 178, "anticipation": 156, "surprise": 76, "fear": 85, "sadness": 102}, "word_freq": {"wedding": 107, "drama": 69, "tammy": 58, "day": 55, "friends": 44, "like": 41, "would": 40, "want": 37, "friend": 35, "dress": 31, "let": 31, "life": 29, "even": 28, "people": 26, "fianc\u00e9": 25, "married": 21, "one": 19, "know": 19, "amy": 19, "ywbta": 19, "person": 19, "really": 19, "op": 17, "nta": 17, "also": 17, "still": 17, "fiance": 17, "cut": 17, "get": 17, "think": 16}, "counts": {"nta_count": 17, "yta_count": 12, "esh_count": 8, "info_count": 3, "nah_count": 0}}