{"id": 8966, "afinn": 333.0, "emotion": {"positive": 1399, "trust": 1030, "anger": 318, "disgust": 218, "negative": 653, "sadness": 359, "anticipation": 665, "joy": 864, "surprise": 358, "fear": 293}, "word_freq": {"friend": 245, "feelings": 166, "go": 162, "trip": 158, "pay": 136, "friendship": 136, "would": 136, "friends": 131, "ticket": 116, "think": 112, "like": 101, "nta": 99, "someone": 89, "get": 86, "op": 76, "time": 76, "still": 70, "want": 67, "people": 65, "flight": 61, "really": 61, "going": 61, "person": 58, "way": 57, "relationship": 56, "said": 55, "one": 54, "make": 49, "romantic": 47, "even": 45}, "counts": {"nta_count": 99, "yta_count": 27, "esh_count": 10, "info_count": 7, "nah_count": 3}}