{"id": 9524, "afinn": 178.0, "emotion": {"positive": 452, "trust": 219, "anger": 133, "disgust": 95, "negative": 275, "joy": 223, "fear": 137, "sadness": 173, "anticipation": 184, "surprise": 78}, "word_freq": {"eat": 68, "biscuits": 54, "nta": 53, "mom": 49, "would": 48, "like": 37, "make": 34, "something": 31, "food": 31, "could": 27, "mother": 24, "way": 24, "ginger": 22, "hard": 21, "also": 20, "baker": 19, "enjoy": 18, "someone": 16, "even": 16, "want": 16, "one": 15, "nerve": 15, "get": 15, "able": 15, "think": 14, "know": 14, "jaw": 14, "good": 14, "sounds": 14, "tea": 14}, "counts": {"nta_count": 53, "yta_count": 1, "esh_count": 0, "info_count": 0, "nah_count": 0}}